pycapital/__init__.py
pycapital/cli.py
pycapital/country_data.py
pycapital/pycapital.py
pycapital-0.2.0.dist-info/DESCRIPTION.rst
pycapital-0.2.0.dist-info/METADATA
pycapital-0.2.0.dist-info/RECORD
pycapital-0.2.0.dist-info/WHEEL
pycapital-0.2.0.dist-info/entry_points.txt
pycapital-0.2.0.dist-info/metadata.json
pycapital-0.2.0.dist-info/top_level.txt
