Metadata-Version: 2.0
Name: pycapital
Version: 0.2.0
Summary: Accepts country names and displays their capitals.
Home-page: https://github.com/terrameijar/pycapital
Author: Vuyisile Ndlovu
Author-email: terrameijar@gmail.com
License: MIT license
Keywords: pycapital
Platform: UNKNOWN
Classifier: Development Status :: 2 - Pre-Alpha
Classifier: Intended Audience :: Developers
Classifier: License :: OSI Approved :: MIT License
Classifier: Natural Language :: English
Classifier: Programming Language :: Python :: 2
Classifier: Programming Language :: Python :: 2.7
Classifier: Programming Language :: Python :: 3
Classifier: Programming Language :: Python :: 3.4
Classifier: Programming Language :: Python :: 3.5
Classifier: Programming Language :: Python :: 3.6
Requires-Dist: Click (>=6.0)
